{
    "Addimage": false,
    "Images": {},
    "Img": {},
    "pqr":{},
    "pinv":{},
    "proall":{},
    "antijs":{},
    "protect":{},
    "SKAdmin": {},
    "SKGfoto": {},
    "SKSDadmin": false,
    "SKSDstaff": false,
    "SKSadmin": false,
    "SKSstaff": false,
    "SKStaff": {},
    "SKautojoin": true,
    "SKautoread": false,
    "SKautoscan": false,
    "SKblacklist": {
        "u0f3ff7c8aba42b6725638265658aa5b1": true
    },
    "SKdblacklist": false,
    "SKfoto": {},
    "SKgreet": {},
    "SKlimit": 1,
    "SKmessage": "Hallo...",
    "SKmessage1": "Minat? Chat http://line.me/ti/p/~dhenz415",
    "SKprotcancel": {},
    "SKprotinvite": {},
    "SKprotkick": {},
    "SKprotqr": {},
    "SKreadMember": {},
    "SKreadPoint": {},
    "SKwblacklist": false,
    "autoAdd": true,
    "autoJoin": true,
    "autoJoinTicket": true,
    "autoLeave": false,
    "autoRead": false,
    "autoReject": false,
    "changeGroupPicture": false,
    "changePicture": false,
    "keyCommand": "",
    "restartBot": {},
    "restartPoint": {},
    "server": {},
    "userAgent": {}
}
